mkdocs_extrafiles/__init__.py
mkdocs_extrafiles/_version.py
mkdocs_extrafiles/plugin.py
mkdocs_extrafiles-1.0.1.dist-info/METADATA
mkdocs_extrafiles-1.0.1.dist-info/WHEEL
mkdocs_extrafiles-1.0.1.dist-info/entry_points.txt
mkdocs_extrafiles-1.0.1.dist-info/licenses/LICENSE
mkdocs_extrafiles-1.0.1.dist-info/RECORD
