Metadata-Version: 2.4
Name: mkdocs-extrafiles
Version: 1.0.1
Summary: A plugin for MkDocs plugin that allows you to add files from outside your `docs_dir`.
Project-URL: Homepage, https://paddy74.github.io/mkdocs-extrafiles/
Project-URL: Changelog, https://paddy74.github.io/mkdocs-extrafiles/about/changelog/
Project-URL: Documentation, https://paddy74.github.io/mkdocs-extrafiles/
Project-URL: Source, https://github.com/paddy74/mkdocs-extrafiles/
License:                     GNU GENERAL PUBLIC LICENSE
License-File: LICENSE
Keywords: mkdocs,mkdocs-plugin
Requires-Python: >=3.11
Requires-Dist: mkdocs>=1.6.1
Provides-Extra: build
Requires-Dist: uv~=0.8.17; extra == 'build'
